pyramid_server_test.py
pytest_pyramid_server.py
pytest_pyramid_server-1.8.0.dist-info/LICENSE
pytest_pyramid_server-1.8.0.dist-info/METADATA
pytest_pyramid_server-1.8.0.dist-info/WHEEL
pytest_pyramid_server-1.8.0.dist-info/entry_points.txt
pytest_pyramid_server-1.8.0.dist-info/top_level.txt
pytest_pyramid_server-1.8.0.dist-info/RECORD
