Metadata-Version: 2.1
Name: pytest-pyramid-server
Version: 1.8.0
Summary: Pyramid server fixture for py.test
Home-page: https://github.com/man-group/pytest-plugins
Author: Edward Easton
Author-email: eeaston@gmail.com
License: MIT license
Platform: unix
Platform: linux
Classifier: License :: OSI Approved :: MIT License
Classifier: Development Status :: 5 - Production/Stable
Classifier: Topic :: Software Development :: Libraries
Classifier: Topic :: Software Development :: Testing
Classifier: Topic :: Utilities
Classifier: Intended Audience :: Developers
Classifier: Operating System :: POSIX
Classifier: Framework :: Pyramid
Classifier: Programming Language :: Python :: 3.6
Classifier: Programming Language :: Python :: 3.7
Requires-Python: >=3.6
License-File: LICENSE
Requires-Dist: pytest-server-fixtures
Requires-Dist: pytest
Requires-Dist: pyramid
Requires-Dist: waitress
Requires-Dist: six
Provides-Extra: tests
Requires-Dist: pyramid-debugtoolbar ; extra == 'tests'
